stldecompose/__init__.py
stldecompose/__version__.py
stldecompose/forecast_funcs.py
stldecompose/stl.py
stldecompose-0.0.3.dist-info/DESCRIPTION.rst
stldecompose-0.0.3.dist-info/METADATA
stldecompose-0.0.3.dist-info/RECORD
stldecompose-0.0.3.dist-info/WHEEL
stldecompose-0.0.3.dist-info/metadata.json
stldecompose-0.0.3.dist-info/top_level.txt
